socHACKi/__init__.py
socHACKi/socHACKiCommunicationsPackage.py
socHACKi/socHACKiDigitalPackage.py
socHACKi/socHACKiMathPackage.py
socHACKi/socHACKiSignalProcessingPackage.py
socHACKi/socHACKiTypeConversionPackage.py
socHACKi/socHACKiUtilityPackage.py
socHACKi-0.0.0.dist-info/DESCRIPTION.rst
socHACKi-0.0.0.dist-info/METADATA
socHACKi-0.0.0.dist-info/RECORD
socHACKi-0.0.0.dist-info/WHEEL
socHACKi-0.0.0.dist-info/metadata.json
socHACKi-0.0.0.dist-info/top_level.txt
